{
  "urls": [
    {
      "name": "Youtube",
      "url": "http://youtube.com"
    },
    {
      "name": "google",
      "url": "http://google.com"
    },
    {
      "name": "archive",
      "url": "http://archive.org"
    },
    {
      "name": "archive",
      "url": "http://archive.org"
    },
    {
      "name": "uol",
      "url": "http://uol.com.br"
    },
    {
      "name": "google",
      "url": "http://google.com"
    },
    {
      "name": "google",
      "url": "http://google.com"
    }
  ]
}